{
  "$id": "https://finstack.dev/schemas/instrument/1/fixed_income/bond_future.schema.json",
  "$schema": "http://json-schema.org/draft-07/schema#",
  "additionalProperties": false,
  "description": "Bond future contract with deliverable basket and conversion factors",
  "examples": [
    {
      "instrument": {
        "spec": {
          "attributes": {
            "meta": {},
            "tags": []
          },
          "contract_specs": {
            "calendar_id": "nyse",
            "contract_size": 100000.0,
            "settlement_days": 2,
            "standard_coupon": 0.06,
            "standard_maturity_years": 10.0,
            "tick_size": 0.015625,
            "tick_value": 15.625
          },
          "ctd_bond_id": "US912828XG33",
          "deliverable_basket": [
            {
              "bond_id": "US912828XG33",
              "conversion_factor": 0.8234
            }
          ],
          "delivery_end": "2025-03-31",
          "delivery_start": "2025-03-21",
          "discount_curve_id": "USD-TREASURY",
          "expiry": "2025-03-20",
          "id": "TYH5",
          "notional": {
            "amount": "1000000",
            "currency": "USD"
          },
          "position": "long",
          "quoted_price": 125.5
        },
        "type": "bond_future"
      },
      "schema": "finstack.instrument/1"
    }
  ],
  "properties": {
    "instrument": {
      "description": "The Bond Future instrument definition",
      "type": "object"
    },
    "schema": {
      "const": "finstack.instrument/1",
      "description": "Schema version identifier",
      "type": "string"
    }
  },
  "required": [
    "schema",
    "instrument"
  ],
  "title": "Bond Future",
  "type": "object"
}
