{
  "schema": "finstack.calibration",
  "plan": {
    "id": "issuer_a_hazard",
    "description": "Single-name hazard curve for Issuer-A, bootstrapped from CDS par spreads against a USD-OIS discount curve provided via initial_market. Demonstrates Track A step-on-snapshot composition: a hazard calibration step runs against a discount curve carried through unchanged from initial_market. Recovery rate 0.4 follows the ISDA CDS standard model convention for senior unsecured single-name CDS.",
    "quote_sets": {
      "issuer_a_cds_quotes": [
        {
          "class": "cds",
          "type": "cds_par_spread",
          "id": "ISSUER-A-CDS-1Y",
          "entity": "Issuer-A",
          "convention": {
            "currency": "USD",
            "doc_clause": "isda_na"
          },
          "pillar": {
            "tenor": {
              "count": 1,
              "unit": "years"
            }
          },
          "spread_bp": 80.0,
          "recovery_rate": 0.4
        },
        {
          "class": "cds",
          "type": "cds_par_spread",
          "id": "ISSUER-A-CDS-3Y",
          "entity": "Issuer-A",
          "convention": {
            "currency": "USD",
            "doc_clause": "isda_na"
          },
          "pillar": {
            "tenor": {
              "count": 3,
              "unit": "years"
            }
          },
          "spread_bp": 110.0,
          "recovery_rate": 0.4
        },
        {
          "class": "cds",
          "type": "cds_par_spread",
          "id": "ISSUER-A-CDS-5Y",
          "entity": "Issuer-A",
          "convention": {
            "currency": "USD",
            "doc_clause": "isda_na"
          },
          "pillar": {
            "tenor": {
              "count": 5,
              "unit": "years"
            }
          },
          "spread_bp": 130.0,
          "recovery_rate": 0.4
        },
        {
          "class": "cds",
          "type": "cds_par_spread",
          "id": "ISSUER-A-CDS-7Y",
          "entity": "Issuer-A",
          "convention": {
            "currency": "USD",
            "doc_clause": "isda_na"
          },
          "pillar": {
            "tenor": {
              "count": 7,
              "unit": "years"
            }
          },
          "spread_bp": 145.0,
          "recovery_rate": 0.4
        },
        {
          "class": "cds",
          "type": "cds_par_spread",
          "id": "ISSUER-A-CDS-10Y",
          "entity": "Issuer-A",
          "convention": {
            "currency": "USD",
            "doc_clause": "isda_na"
          },
          "pillar": {
            "tenor": {
              "count": 10,
              "unit": "years"
            }
          },
          "spread_bp": 155.0,
          "recovery_rate": 0.4
        }
      ]
    },
    "steps": [
      {
        "id": "ISSUER-A-CDS",
        "quote_set": "issuer_a_cds_quotes",
        "kind": "hazard",
        "curve_id": "ISSUER-A-CDS",
        "entity": "Issuer-A",
        "seniority": "senior",
        "currency": "USD",
        "base_date": "2026-05-08",
        "discount_curve_id": "USD-OIS",
        "recovery_rate": 0.4,
        "notional": 1.0,
        "method": "Bootstrap",
        "interpolation": "linear",
        "par_interp": "Linear"
      }
    ],
    "settings": {}
  },
  "initial_market": {
    "version": 2,
    "curves": [
      {
        "type": "discount",
        "id": "USD-OIS",
        "base": "2026-05-08",
        "day_count": "Act360",
        "knot_points": [
          [0.0, 1.0],
          [0.25, 0.98758],
          [0.5, 0.97531],
          [1.0, 0.95123],
          [2.0, 0.90484],
          [5.0, 0.77880],
          [10.0, 0.60653]
        ],
        "interp_style": "log_linear",
        "extrapolation": "flat_forward",
        "min_forward_rate": null,
        "allow_non_monotonic": false,
        "min_forward_tenor": 1e-6,
        "rate_calibration": null
      }
    ],
    "fx": null,
    "surfaces": [],
    "prices": {},
    "series": [],
    "inflation_indices": [],
    "dividends": [],
    "credit_indices": [],
    "fx_delta_vol_surfaces": [],
    "vol_cubes": [],
    "collateral": {}
  }
}
